Workbook
Name C2ؤ1451: #REF!

Sheet 00_Raw
A1: order_id | B1: order_date | C1: order_time | D1: channel | E1: item_name | F1: category | G1: quantity | H1: unit_price | I1: total_price | J1: payment_method | K1: discount_pct | L1: customer_rating | M1: server_name
A2: ORD-00001 | B2: 2026-02-01 | C2: 14:55 | D2: Dine-in | E2: Tea | F2: Beverages | G2: 2 | H2: 1000 | I2: 2000 | J2: Cash | M2: Noor Kadhim
A3: ORD-00002 | B3: 2026-02-01 | C3: 20:24 | D3: Dine-in | E3: Chicken Tikka | F3: Grills | G3: 3 | H3: 15000 | I3: 45000 | J3: Card | M3: Ali Hassan
A4: ORD-00003 | B4: 2026-02-01 | C4: 20:26 | D4: Dine-in | E4: Falafel Sandwich | F4: Sandwiches | G4: 1 | H4: 3000 | I4: 3000 | J4: Cash | M4: Mustafa Karim
A5: ORD-00003 | B5: 2026-02-01 | C5: 20:26 | D5: Dine-in | E5: Falafel Sandwich | F5: Sandwiches | G5: 1 | H5: 3000 | I5: 3000 | J5: Cash | M5: Mustafa Karim
A6: ORD-00004 | B6: 2026-02-01 | C6: 20:50 | D6: Delivery | E6: Hummus | F6: Appetizers | G6: 1 | H6: 4000 | I6: 4000 | J6: Cash | M6: Zainab Salim
A7: ORD-00005 | B7: 2026-02-01 | C7: 22:04 | D7: Delivery | E7: Mixed Grill Platter | F7: Grills | G7: 1 | H7: 25000 | I7: 25000 | J7: Card | K7: 10 | L7: 5 | M7: Mustafa Karim
A8: ORD-00006 | B8: 2026-02-01 | C8: 22:53 | D8: Delivery | E8: Lamb Kebab | F8: Grills | G8: 1 | H8: 18000 | I8: 18000 | J8: Cash | M8: Ali Hassan
A9: ORD-00007 | B9: 2026-02-02 | C9: 20:15 | D9: Dine-in | E9: Soft Drink | F9: Beverages | G9: 1 | H9: 1500 | I9: 1500 | J9: Cash | L9: 4 | M9: Ali Hassan
A10: ORD-00008 | B10: 2026-02-02 | C10: 20:25 | D10: Dine-in | E10: Tea | F10: Beverages | G10: 1 | H10: 1000 | I10: 1000 | J10: Cash | L10: 3 | M10: Ali Hassan
A11: ORD-00009 | B11: 2026-02-02 | C11: 20:45 | D11: Takeaway | E11: Chicken Tikka | F11: Grills | G11: 1 | H11: 15000 | I11: 15000 | J11: Card | M11: Ali Hassan
A12: ORD-00010 | B12: 2026-02-02 | C12: 20:50 | D12: Dine-in | E12: Soft Drink | H12: 1500 | I12: 1500 | J12: Cash | M12: Omar Jabbar
A13: ORD-00011 | B13: 2026-02-02 | C13: 21:26 | D13: Dine-in | E13: Shwarma Sandwich | F13: Sandwiches | G13: 1 | H13: 5000 | I13: 5000 | J13: Cash | M13: Zainab Salim
A14: ORD-00012 | B14: 02/02/2026 | C14: 23:49 | D14: Delivery | E14: Chicken Sandwich | F14: Sandwiches | G14: 1 | H14: 6000 | I14: 6000 | J14: Cash | L14: 4 | M14: Mustafa Karim
A15: ORD-00013 | B15: 2026-02-03 | C15: 19:22 | D15: dine in | E15: Tea | F15: Beverages | G15: 1 | I15: 1000 | J15: Cash | L15: 4 | M15: Noor Kadhim
A16: ORD-00014 | B16: 2026-02-03 | C16: 20:11 | D16: Dine-in | E16: CHICKEN TIKKA | F16: Grills | G16: 1 | I16: 13500 | J16: Cash | K16: 10 | M16: Omar Jabbar
A17: ORD-00015 | B17: 2026-02-03 | C17: 20:16 | D17: Delivery | E17: Falafel Sandwich | F17: Sandwiches | H17: 3000 | I17: 3000 | J17: Card | L17: 3 | M17: Zainab Salim
A18: ORD-00016 | B18: 2026-02-03 | C18: 22:17 | D18: Delivery | E18: Fattoush Salad | F18: Appetizers | G18: 2 | H18: 5000 | I18: 10000 | J18: Cash | L18: 4 | M18: Ali Hassan
A19: ORD-00017 | B19: 2026-02-03 | C19: 22:24 | D19: Delivery | E19: Tea | G19: 1 | H19: 1000 | I19: 1000 | J19: Cash | M19: noor kadhim
A20: ORD-00018 | B20: 2026-02-04 | C20: 17:58 | D20: Dine-in | E20: Shawarma Sandwich | G20: 1 | H20: 5000 IQD | I20: 5000 | J20: Cash | M20: Ali Hassan
A21: ORD-00019 | B21: 2026-02-04 | C21: 19:59 | D21: Takeaway | E21: Kunafah | F21: Desserts | G21: 1 | H21: 7000 | I21: 7000 IQD | J21: Card | M21: Mustafa Karim
A22: ORD-00020 | B22: 2026-02-04 | C22: 20:23 | D22: Dine-in | E22: Hummus | F22: Appetizers | G22: 2 | H22: 4000 | I22: 8000 | J22: Cash | M22: Omar Jabbar
A23: ORD-00021 | B23: 2026-02-04 | C23: 20:56 | D23: Dine-in | E23: Mixed Grill Platter | F23: Grills | G23: 1 | H23: 25000 | I23: 25000 | J23: Cash | M23: Ali Hassan
A24: ORD-00022 | B24: 2026-02-04 | C24: 22:48 | D24: Delivery | E24: Fattoush Salad | F24: Appetizers | G24: 1 | H24: 5000 | I24: 4000 | J24: Cash | K24: 20 | M24: Zainab Salim
A25: ORD-00023 | B25: 2026-02-05 | C25: 13:57 | D25: Dine-in | E25: Tea | F25: Beverages | G25: 1 | H25: 1000 | I25: 1000 | J25: Cash | M25: Noor Kadhim
A26: ORD-00024 | B26: 2026-02-05 | C26: 17:33 | D26: takeaway | E26: Chicken Tikka | F26: Grills | G26: 2 | H26: 15000 | I26: 30000 IQD | J26: CASH | L26: 5 | M26: Mustafa Karim
A27: ORD-00025 | B27: 2026-02-05 | C27: 17:42 | D27: Dine-in | E27: Falafel Sandwich | F27: Sandwiches | G27: 1 | H27: 3,000 | I27: 3000 | J27: Cash | M27: Mustafa Karim
A28: ORD-00026 | B28: 2026-02-05 | C28: 18:31 | D28: dine-in | E28: Soft Drink | F28: Beverages | G28: 1 | H28: 1500 | I28: 1500 | J28: Cash | M28: Omar Jabbar
A29: ORD-00027 | B29: 2026-02-05 | C29: 18:44 | D29: Takeaway | E29: Chicken Sandwich | G29: 1 | H29: 6000 | I29: 6000 | J29: Cash | M29: Ali Hassan
A30: ORD-00028 | B30: 2026-02-05 | C30: 19:01 | D30: Dine-in | E30: Lamb Kebab | F30: Grills | G30: 2 | H30: 18000 | I30: 36000 | J30: Cash | M30: Zainab Salim
A31: ORD-00029 | B31: 2026-02-05 | C31: 19:17 | D31: Delivery | E31: Lamb Kebab | F31: Grills | G31: 1 | H31: 18000 | I31: 18000 | J31: Cash | K31: 15 | M31: Zainab Salim
A32: ORD-00030 | B32: 2026-02-05 | C32: 20:00 | D32: Delivery | E32: Shish Tawook | F32: Grills | G32: 3 | H32: 16000 | I32: 48000 | J32: Card | M32: Ali Hassan
A33: ORD-00031 | B33: 2026-02-05 | C33: 21:19 | D33: Dine-in | E33: Chicken Sandwich | F33: Sandwiches | G33: 1 | H33: 6000 | I33: 6000 | J33: Cash | M33: Omar Jabbar
A34: ORD-00032 | B34: 2026-02-05 | C34: 21:25 | D34: Dine-in | E34: Shawarma Sandwich | F34: Sandwiches | G34: 1 | H34: 5000 | I34: 5000 | J34: Cash | M34: Noor Kadhim
A35: ORD-00033 | B35: 2026-02-05 | C35: 21:55 | D35: Dine-in | E35: Tea | G35: 2 | H35: 1000 | I35: 2000 | J35: Cash | M35: omar jabbar
A36: ORD-00034 | B36: 2026-02-05 | C36: 22:04 | D36: Delivery | E36: Lamb Kebab | F36: Grills | G36: 1 | H36: 18000 | I36: 18000 | J36: Cash | M36: Ali Hassan
A37: ORD-00035 | B37: 2026-02-05 | C37: 22:30 | D37: Dine-in | E37: Softdrink | F37: Beverages | G37: 1 | I37: 1350 | J37: Cash | K37: 10 | M37: Omar Jabbar
A38: ORD-00036 | B38: 2026-02-05 | C38: 22:37 | D38: Dine-in | E38: Baklava | F38: Desserts | G38: 1 | H38: 6000 | I38: 6000 | J38: Cash | M38: Noor Kadhim
A39: ORD-00037 | B39: 2026-02-05 | C39: 23:14 | D39: Dine-in | E39: Tea | F39: Beverages | G39: 1 | H39: 1000 | I39: 1000 | J39: Cash | L39: 5 | M39: Zainab Salim
A40: ORD-00038 | B40: 2026-02-06 | C40: 11:27 | D40: Dine-in | E40: Lamb Kebab | F40: Grills | G40: 1 | H40: 18000 | I40: 18000 | J40: Cash | M40: omar jabbar
A41: ORD-00039 | B41: 06/02/2026 | C41: 12:12 | D41: Dine-in | E41: Tea | F41: Beverages | G41: 1 | H41: 1000 | I41: 1000 | J41: Card | L41: 4 | M41: Noor Kadhim
A42: ORD-00040 | B42: 2026-02-06 | C42: 14:17 | D42: Takeaway | E42: Baklava | F42: Desserts | G42: 1 | H42: 6000 | I42: 6000 | J42: Cash | L42: 3 | M42: Zainab Salim
A43: ORD-00041 | B43: 2026-02-06 | C43: 14:42 | D43: Dine-in | E43: Soft Drink | F43: Beverages | G43: 1 | I43: 1500 | J43: Cash | L43: 5 | M43: Noor Kadhim
A44: ORD-00042 | B44: February 6 2026 | C44: 16:36 | D44: Delivery | E44: Baklava | F44: Desserts | G44: 1 | H44: 6000 | I44: 6000 | J44: Card | L44: 4 | M44: ali hassan
A45: ORD-00043 | B45: 2026-02-06 | C45: 19:23 | D45: Dine-in | E45: Chicken Sandwich | F45: Sandwiches | G45: 2 | H45: 6000 | I45: 12000 | J45: Cash | M45: Omar Jabbar
A46: ORD-00044 | B46: 2026-02-06 | C46: 20:56 | D46: Dine-in | E46: Shwarma Sandwich | F46: Sandwiches | G46: 1 | H46: 5000 | I46: 5000 | J46: Card | M46: Mustafa Karim
A47: ORD-00045 | B47: 2026-02-06 | C47: 21:47 | D47: Dine-in | E47: shawarma sandwich | F47: Sandwiches | G47: 2 | H47: 5000 | I47: 8500 | J47: Cash | K47: 15 | M47: Ali Hassan
A48: ORD-00046 | B48: 2026-02-06 | C48: 23:53 | D48: dine-in | E48: Shawarma Sandwich | F48: Sandwiches | G48: 1 | H48: 5000 | I48: 5000 | J48: Card | L48: 5 | M48: Ali Hassan
A49: ORD-00047 | B49: 2026-02-07 | C49: 11:35 | D49: Dine-in | E49: Tea | F49: Beverages | G49: 3 | H49: 1000 | I49: 3000 | J49: Card | L49: 4 | M49: Mustafa Karim
A50: ORD-00048 | B50: 2026-02-07 | C50: 19:09 | D50: Takeaway | E50: Chicken Sandwich | F50: Sandwiches | G50: 1 | H50: 6000 | I50: 6000 | J50: Cash | L50: 4 | M50: Zainab Salim
A51: ORD-00049 | B51: 2026-02-07 | C51: 21:04 | D51: Takeaway | E51: Fresh Lemon Mint | F51: Beverages | G51: 1 | H51: 3000 | I51: 3000 | J51: Cash | M51: Omar Jabbar
A52: ORD-00050 | B52: 2026-02-07 | C52: 21:41 | D52: Dine-in | E52: Soft Drink | F52: Beverages | H52: 1500 | I52: 1500 | J52: Card | M52: Noor Kadhim
A53: ORD-00051 | B53: 2026-02-07 | C53: 21:43 | D53: Dine-in | E53: Hummus | F53: Appetizers | G53: 1 | H53: 4000 | J53: Cash | M53: Ali Hassan
A54: ORD-00052 | B54: February 7 2026 | C54: 22:07 | D54: delivery | E54: Chicken Sandwich | F54: Sandwiches | G54: 1 | H54: 6000 | I54: 6000 | J54: Cash | M54: Noor Kadhim
A55: ORD-00053 | B55: 2026-02-07 | C55: 22:40 | D55: Delivery | E55: Shawarma Sandwich | F55: Sandwiches | G55: 2 | H55: 5000 | I55: 10000 | J55: Cash | M55: Mustafa Karim
A56: ORD-00054 | B56: 2026-02-08 | C56: 19:18 | D56: DINE-IN | E56: Hummus | F56: Appetizers | H56: 4000 | I56: 3600 | J56: Cash | K56: 10 | L56: 3 | M56: Zainab Salim
A57: ORD-00055 | B57: 2026-02-08 | C57: 19:37 | D57: Dine-in | E57: shish tawook | F57: Grills | G57: 1 | H57: 16000 | I57: 16,000 IQD | J57: Cash | M57: Omar Jabbar
A58: ORD-00056 | B58: 2026-02-08 | C58: 20:23 | D58: Dine-in | E58: Fresh Lemon Mint | F58: Beverages | G58: 2 | H58: 3000 | I58: 6000 | J58: Cash | L58: 4 | M58: mustafa karim
A59: ORD-00057 | B59: 2026-02-08 | C59: 21:17 | D59: Takeaway | E59: Tea | F59: Beverages | G59: 2 | H59: 1000 | I59: 2000 | J59: Cash | L59: 4 | M59: Omar Jabbar
A60: ORD-00058 | B60: 2026-02-08 | C60: 21:41 | D60: Dine-in | E60: Falafel Sandwich | F60: Sandwiches | G60: 1 | H60: 3000 | I60: 3000 | J60: Cash | M60: Ali Hassan
A61: ORD-00059 | B61: 2026-02-09 | C61: 14:29 | D61: Dine-in | E61: Shawarma Sandwich | F61: Sandwiches | G61: 1 | H61: 5000 | I61: 4500 | J61: Cash | K61: 10 | M61: Noor Kadhim
A62: ORD-00060 | B62: 2026-02-09 | C62: 20:01 | D62: Dine-in | E62: Fattoush Salad | F62: Appetizers | G62: 3 | H62: 5000 | I62: 15000 | J62: Cash | L62: 4 | M62: Noor Kadhim
A63: ORD-00061 | B63: 2026-02-09 | C63: 21:06 | D63: Dine-in | E63: Soft Drink | F63: Beverages | G63: 1 | H63: 1500 | I63: 1500 | J63: Cash | M63: Zainab Salim
A64: ORD-00062 | B64: 2026-02-09 | C64: 21:42 | D64: delivary | E64: Humus | F64: Appetizers | G64: 1 | H64: 4000 | I64: 4000 | J64: Cash | L64: 4 | M64: Omar Jabbar
A65: ORD-00063 | B65: 2026-02-09 | C65: 22:05 | D65: Delivery | E65: Shawarma Sandwich | F65: Sandwiches | G65: 1 | H65: 5000 | I65: 5000 | J65: Cash | M65: Ali Hassan
A66: ORD-00064 | B66: 09/02/2026 | C66: 22:58 | D66: Dine-in | E66: Tea | F66: Beverages | G66: 1 | H66: 1000 | I66: 1000 | J66: Cash | M66: Mustafa Karim
A67: ORD-00065 | B67: 2026-02-10 | C67: 18:39 | D67: Dine-in | E67: Fresh Lemon Mint | F67: Beverages | G67: 1 | H67: 3000 | I67: 3000 | J67: Cash | M67: Noor Kadhim
A68: ORD-00066 | B68: 10/02/2026 | C68: 20:04 | D68: Dine-in | E68: Soft Drink | F68: Beverages | G68: 1 | I68: 1350 | J68: Cash | K68: 10 | L68: 4 | M68: Mustafa Karim
A69: ORD-00067 | B69: 2026-02-10 | C69: 20:45 | D69: Dine-in | E69: Lamb Kebab | F69: Grills | G69: 1 | H69: 18000 | I69: 18000 | J69: Cash | L69: 4 | M69: mustafa karim
A70: ORD-00068 | B70: 2026-02-10 | C70: 20:51 | D70: Dine-in | E70: Softdrink | F70: Beverages | G70: 1 | I70: 1200 | J70: Cash | K70: 20 | M70: Omar Jabbar
A71: ORD-00069 | B71: February 10 2026 | C71: 22:40 | D71: Dine-in | E71: Soft Drink | F71: Beverages | G71: 2 | H71: 1500 | J71: Cash | M71: Noor Kadhim
A72: ORD-00070 | B72: 2026-02-10 | C72: 22:44 | D72: Takeaway | E72: Tea | F72: Beverages | G72: 2 | H72: 1000 | I72: 2000 | J72: Card | M72: Noor Kadhim
A73: ORD-00070 | B73: 2026-02-10 | C73: 22:44 | D73: Takeaway | E73: Tea | F73: Beverages | G73: 2 | H73: 1000 | I73: 2000 | J73: Card | M73: Noor Kadhim
A74: ORD-00071 | B74: 2026-02-10 | C74: 23:30 | D74: Takeaway | E74: CHICKEN TIKKA | F74: Grills | G74: 2 | I74: 30000 | J74: Cash | L74: 4 | M74: Noor Kadhim
A75: ORD-00072 | B75: 2026-02-11 | C75: 13:37 | D75: Dine-in | E75: Hommus | F75: Appetizers | G75: 1 | I75: 4000 | J75: Cash | M75: Ali Hassan
A76: ORD-00073 | B76: 11/02/2026 | C76: 19:06 | D76: Dine-in | E76: soft drink | G76: 1 | H76: 1500 | I76: 1500 | J76: Cash | L76: 4 | M76: Mustafa Karim
A77: ORD-00074 | B77: 2026-02-11 | C77: 20:01 | D77: Dine-in | E77: Lamb Kebab | F77: Grills | G77: 1 | I77: 18000 | J77: Cash | M77: Omar Jabbar
A78: ORD-00075 | B78: 2026-02-11 | C78: 20:29 | D78: Dine-in | E78: Chicken Sandwich | F78: Sandwiches | G78: 2 | H78: 6000 | I78: 12000 | J78: Cash | L78: 4 | M78: Zainab Salim
A79: ORD-00076 | B79: 2026-02-11 | C79: 21:07 | D79: Dine-in | E79: Mixed Grill Platter | F79: Grills | G79: 1 | H79: 25000 | I79: 25000 | J79: Card | M79: Noor Kadhim
A80: ORD-00077 | B80: 2026-02-12 | C80: 12:04 | D80: Takeaway | E80: Tea | F80: Beverages | G80: 1 | H80: 1000 | I80: 1000 | J80: Cash | M80: Noor Kadhim
A81: ORD-00078 | B81: 2026-02-12 | C81: 19:23 | D81: Dine-in | E81: Shish Tawook | F81: Grills | G81: 1 | H81: 16000 | I81: 16000 | J81: Card | M81: Mustafa Karim
A82: ORD-00079 | B82: 2026-02-12 | C82: 20:00 | D82: Takeaway | E82: Chicken Sandwich | F82: Sandwiches | G82: 1 | H82: 6000 | I82: 6000 | J82: Cash | M82: Noor Kadhim
A83: ORD-00080 | B83: 2026-02-12 | C83: 20:31 | D83: Dine-in | E83: Mixed Grill Platter | F83: Grills | G83: 1 | H83: 25000 | I83: 22500 | J83: Cash | K83: 10 | L83: 4 | M83: Zainab Salim
A84: ORD-00081 | B84: 2026-02-12 | C84: 20:35 | D84: Dine-in | E84: Falafel Sandwich | F84: Sandwiches | G84: 1 | H84: 3000 | I84: 3000 | J84: Cash | L84: 4 | M84: Ali Hassan
A85: ORD-00082 | B85: 2026-02-12 | C85: 21:16 | D85: Takeaway | E85: Shawarma Sandwich | F85: Sandwiches | G85: 1 | H85: 5000 | I85: 5000 | J85: Cash | M85: Ali Hassan
A86: ORD-00082 | B86: 2026-02-12 | C86: 21:16 | D86: Takeaway | E86: Shawarma Sandwich | F86: Sandwiches | G86: 1 | H86: 5000 | I86: 5000 | J86: Cash | M86: Ali Hassan
A87: ORD-00083 | B87: 2026-02-12 | C87: 21:52 | D87: Dine-in | E87: Falafel Sandwich | F87: Sandwiches | G87: 1 | H87: 3000 | I87: 3000 | J87: Cash | L87: 3 | M87: ali hassan
A88: ORD-00084 | B88: 2026-02-12 | C88: 23:07 | D88: Dine-in | E88: Shish Tawook | F88: Grills | G88: 3 | H88: 16000 | I88: 48000 | J88: Cash | K88: 10 | M88: Omar Jabbar
A89: ORD-00085 | B89: 2026-02-12 | C89: 23:27 | D89: Dine-in | E89: Shawarma Sandwich | F89: Sandwiches | G89: 2 | H89: 5000 | I89: 10000 | J89: Card | M89: NOOR KADHIM
A90: ORD-00086 | B90: 2026-02-12 | C90: 23:43 | D90: Dine-in | E90: Lamb Kebab | F90: Grills | G90: 3 | H90: 18000 | I90: 54000 | J90: CASH | M90: Noor Kadhim
A91: ORD-00087 | B91: 2026-02-12 | C91: 23:50 | D91: Dine-in | E91: Fresh Lemon Mint | F91: Beverages | G91: 1 | H91: 3000 | I91: 3000 | J91: Cash | L91: 4 | M91: Mustafa Karim
A92: ORD-00088 | B92: February 13 2026 | C92: 13:55 | D92: Takeaway | E92: Mixed Grill Platter | F92: Grills | G92: 1 | H92: 25000 | I92: 25000 | J92: Cash | M92: Mustafa Karim
A93: ORD-00089 | B93: 2026-02-13 | C93: 14:42 | D93: Dine-in | E93: Baklava | G93: 1 | H93: 6000 | I93: 6000 | J93: Cash | M93: Noor Kadhim
A94: ORD-00090 | B94: 2026-02-13 | C94: 17:49 | D94: Dine-in | E94: Mixed Grill Platter | F94: Grills | G94: 1 | H94: 25000 | I94: 20000 | J94: Cash | K94: 20 | M94: Omar Jabbar
A95: ORD-00091 | B95: 2026-02-13 | C95: 18:05 | D95: Dine-in | E95: Fresh Lemon Mint | F95: Beverages | G95: 1 | H95: 3000 | I95: 3000 | J95: Cash | M95: Omar Jabbar
A96: ORD-00092 | B96: 2026-02-13 | C96: 18:21 | D96: Dine-in | E96: Falafel Sandwich | F96: Sandwiches | G96: 2 | H96: 3000 | I96: 6000 IQD | J96: Cash | M96: Mustafa Karim
A97: ORD-00093 | B97: 2026-02-13 | C97: 19:13 | D97: Dine-in | E97: Tea | F97: Beverages | G97: 2 | H97: 1000 | I97: 2000 | J97: Cash | M97: Noor Kadhim
A98: ORD-00094 | B98: 2026-02-13 | C98: 20:10 | D98: Dine-in | E98: Baklava | F98: Desserts | G98: 1 | H98: 6000 | I98: 6000 | J98: Cash | L98: 4 | M98: Omar Jabbar
A99: ORD-00095 | B99: 2026-02-13 | C99: 20:14 | D99: Dine-in | E99: Falafel Sandwich | F99: Sandwiches | G99: 1 | H99: 3000 | I99: 3000 | J99: Card | M99: ALI HASSAN
A100: ORD-00096 | B100: 13/02/2026 | C100: 20:29 | D100: Dine-in | E100: Falafel Sandwich | F100: Sandwiches | G100: 1 | H100: 3000 | I100: 3000 | J100: Cash | M100: Ali Hassan
...

Sheet 01-clean
A1: order_id | B1: order_date | C1: order_time | D1: Hour | E1: weekday | F1: channel | G1: item_name | H1: category | I1: quantity | J1: unit_price | K1: total_price | L1: payment_method | M1: discount_pct | N1: customer_rating | O1: server_name
A2: ORD-00001 | B2: 46054 | C2: 0.62152778 | D2: =HOUR(C2) -> 14 | E2: =TEXT(B2,"dddd") -> Sunday | F2: Dine-in | G2: Tea | H2: Beverages | I2: 2 | J2: 1000 | K2: 2000 | L2: Cash | M2: 0 | O2: Noor Kadhim
A3: ORD-00002 | B3: 46054 | C3: 0.85 | D3: =HOUR(C3) -> 20 | E3: =TEXT(B3,"dddd") -> Sunday | F3: Dine-in | G3: Chicken Tikka | H3: Grills | I3: 3 | J3: 15000 | K3: 45000 | L3: Card | M3: 0 | O3: Ali Hassan
A4: ORD-00003 | B4: 46054 | C4: 0.85138889 | D4: =HOUR(C4) -> 20 | E4: =TEXT(B4,"dddd") -> Sunday | F4: Dine-in | G4: Falafel Sandwich | H4: Sandwiches | I4: 1 | J4: 3000 | K4: 3000 | L4: Cash | M4: 0 | O4: Mustafa Karim
A5: ORD-00004 | B5: 46054 | C5: 0.86805556 | D5: =HOUR(C5) -> 20 | E5: =TEXT(B5,"dddd") -> Sunday | F5: Delivery | G5: Hummus | H5: Appetizers | I5: 1 | J5: 4000 | K5: 4000 | L5: Cash | M5: 0 | O5: Zainab Salim
A6: ORD-00005 | B6: 46054 | C6: 0.91944444 | D6: =HOUR(C6) -> 22 | E6: =TEXT(B6,"dddd") -> Sunday | F6: Delivery | G6: Mixed Grill Platter | H6: Grills | I6: 1 | J6: 25000 | K6: 22500 | L6: Card | M6: 0.1 | N6: 5 | O6: Mustafa Karim
A7: ORD-00006 | B7: 46054 | C7: 0.95347222 | D7: =HOUR(C7) -> 22 | E7: =TEXT(B7,"dddd") -> Sunday | F7: Delivery | G7: Lamb Kebab | H7: Grills | I7: 1 | J7: 18000 | K7: 18000 | L7: Cash | M7: 0 | O7: Ali Hassan
A8: ORD-00007 | B8: 46055 | C8: 0.84375 | D8: =HOUR(C8) -> 20 | E8: =TEXT(B8,"dddd") -> Monday | F8: Dine-in | G8: Soft Drink | H8: Beverages | I8: 1 | J8: 1500 | K8: 1500 | L8: Cash | M8: 0 | N8: 4 | O8: Ali Hassan
A9: ORD-00008 | B9: 46055 | C9: 0.85069444 | D9: =HOUR(C9) -> 20 | E9: =TEXT(B9,"dddd") -> Monday | F9: Dine-in | G9: Tea | H9: Beverages | I9: 1 | J9: 1000 | K9: 1000 | L9: Cash | M9: 0 | N9: 3 | O9: Ali Hassan
A10: ORD-00009 | B10: 46055 | C10: 0.86458333 | D10: =HOUR(C10) -> 20 | E10: =TEXT(B10,"dddd") -> Monday | F10: Takeaway | G10: Chicken Tikka | H10: Grills | I10: 1 | J10: 15000 | K10: 15000 | L10: Card | M10: 0 | O10: Ali Hassan
A11: ORD-00010 | B11: 46055 | C11: 0.86805556 | D11: =HOUR(C11) -> 20 | E11: =TEXT(B11,"dddd") -> Monday | F11: Dine-in | G11: Soft Drink | H11: =VLOOKUP(G11,'02_Menu_Lookup'!$A$2:$C$16,2,FALSE) -> Beverages | I11: =K11/J11 -> 1 | J11: 1500 | K11: 1500 | L11: Cash | M11: 0 | O11: Omar Jabbar
A12: ORD-00011 | B12: 46055 | C12: 0.89305556 | D12: =HOUR(C12) -> 21 | E12: =TEXT(B12,"dddd") -> Monday | F12: Dine-in | G12: Shawarma Sandwich | H12: Sandwiches | I12: 1 | J12: 5000 | K12: 5000 | L12: Cash | M12: 0 | O12: Zainab Salim
A13: ORD-00012 | B13: 46055 | C13: 0.99236111 | D13: =HOUR(C13) -> 23 | E13: =TEXT(B13,"dddd") -> Monday | F13: Delivery | G13: Chicken Sandwich | H13: Sandwiches | I13: 1 | J13: 6000 | K13: 6000 | L13: Cash | M13: 0 | N13: 4 | O13: Mustafa Karim
A14: ORD-00013 | B14: 46056 | C14: 0.80694444 | D14: =HOUR(C14) -> 19 | E14: =TEXT(B14,"dddd") -> Tuesday | F14: Dine-in | G14: Tea | H14: Beverages | I14: 1 | J14: =K14/I14 -> 1000 | K14: 1000 | L14: Cash | M14: 0 | N14: 4 | O14: Noor Kadhim
A15: ORD-00014 | B15: 46056 | C15: 0.84097222 | D15: =HOUR(C15) -> 20 | E15: =TEXT(B15,"dddd") -> Tuesday | F15: Dine-in | G15: Chicken Tikka | H15: Grills | I15: 1 | J15: 13500 | K15: 12150 | L15: Cash | M15: 0.1 | O15: Omar Jabbar
A16: ORD-00015 | B16: 46056 | C16: 0.84444444 | D16: =HOUR(C16) -> 20 | E16: =TEXT(B16,"dddd") -> Tuesday | F16: Delivery | G16: Falafel Sandwich | H16: Sandwiches | I16: =K16/J16 -> 1 | J16: 3000 | K16: 3000 | L16: Card | M16: 0 | N16: 3 | O16: Zainab Salim
A17: ORD-00016 | B17: 46056 | C17: 0.92847222 | D17: =HOUR(C17) -> 22 | E17: =TEXT(B17,"dddd") -> Tuesday | F17: Delivery | G17: Fattoush Salad | H17: Appetizers | I17: 2 | J17: 5000 | K17: 10000 | L17: Cash | M17: 0 | N17: 4 | O17: Ali Hassan
A18: ORD-00017 | B18: 46056 | C18: 0.93333333 | D18: =HOUR(C18) -> 22 | E18: =TEXT(B18,"dddd") -> Tuesday | F18: Delivery | G18: Tea | H18: =VLOOKUP(G18,'02_Menu_Lookup'!$A$2:$C$16,2,FALSE) -> Beverages | I18: 1 | J18: 1000 | K18: 1000 | L18: Cash | M18: 0 | O18: Noor Kadhim
A19: ORD-00018 | B19: 46057 | C19: 0.74861111 | D19: =HOUR(C19) -> 17 | E19: =TEXT(B19,"dddd") -> Wednesday | F19: Dine-in | G19: Shawarma Sandwich | H19: =VLOOKUP(G19,'02_Menu_Lookup'!$A$2:$C$16,2,FALSE) -> Sandwiches | I19: 1 | J19: 5000 | K19: 5000 | L19: Cash | M19: 0 | O19: Ali Hassan
A20: ORD-00019 | B20: 46057 | C20: 0.83263889 | D20: =HOUR(C20) -> 19 | E20: =TEXT(B20,"dddd") -> Wednesday | F20: Takeaway | G20: Kunafa | H20: Desserts | I20: 1 | J20: 7000 | K20: 7000 | L20: Card | M20: 0 | O20: Mustafa Karim
A21: ORD-00020 | B21: 46057 | C21: 0.84930556 | D21: =HOUR(C21) -> 20 | E21: =TEXT(B21,"dddd") -> Wednesday | F21: Dine-in | G21: Hummus | H21: Appetizers | I21: 2 | J21: 4000 | K21: 8000 | L21: Cash | M21: 0 | O21: Omar Jabbar
A22: ORD-00021 | B22: 46057 | C22: 0.87222222 | D22: =HOUR(C22) -> 20 | E22: =TEXT(B22,"dddd") -> Wednesday | F22: Dine-in | G22: Mixed Grill Platter | H22: Grills | I22: 1 | J22: 25000 | K22: 25000 | L22: Cash | M22: 0 | O22: Ali Hassan
A23: ORD-00022 | B23: 46057 | C23: 0.95 | D23: =HOUR(C23) -> 22 | E23: =TEXT(B23,"dddd") -> Wednesday | F23: Delivery | G23: Fattoush Salad | H23: Appetizers | I23: 1 | J23: 5000 | K23: 4000 | L23: Cash | M23: 0.2 | O23: Zainab Salim
A24: ORD-00023 | B24: 46058 | C24: 0.58125 | D24: =HOUR(C24) -> 13 | E24: =TEXT(B24,"dddd") -> Thursday | F24: Dine-in | G24: Tea | H24: Beverages | I24: 1 | J24: 1000 | K24: 1000 | L24: Cash | M24: 0 | O24: Noor Kadhim
A25: ORD-00024 | B25: 46058 | C25: 0.73125 | D25: =HOUR(C25) -> 17 | E25: =TEXT(B25,"dddd") -> Thursday | F25: Takeaway | G25: Chicken Tikka | H25: Grills | I25: 2 | J25: 15000 | K25: 30000 | L25: Cash | M25: 0 | N25: 5 | O25: Mustafa Karim
A26: ORD-00025 | B26: 46058 | C26: 0.7375 | D26: =HOUR(C26) -> 17 | E26: =TEXT(B26,"dddd") -> Thursday | F26: Dine-in | G26: Falafel Sandwich | H26: Sandwiches | I26: 1 | J26: 3000 | K26: 3000 | L26: Cash | M26: 0 | O26: Mustafa Karim
A27: ORD-00026 | B27: 46058 | C27: 0.77152778 | D27: =HOUR(C27) -> 18 | E27: =TEXT(B27,"dddd") -> Thursday | F27: Dine-in | G27: Soft Drink | H27: Beverages | I27: 1 | J27: 1500 | K27: 1500 | L27: Cash | M27: 0 | O27: Omar Jabbar
A28: ORD-00027 | B28: 46058 | C28: 0.78055556 | D28: =HOUR(C28) -> 18 | E28: =TEXT(B28,"dddd") -> Thursday | F28: Takeaway | G28: Chicken Sandwich | H28: =VLOOKUP(G28,'02_Menu_Lookup'!$A$2:$C$16,2,FALSE) -> Sandwiches | I28: 1 | J28: 6000 | K28: 6000 | L28: Cash | M28: 0 | O28: Ali Hassan
A29: ORD-00028 | B29: 46058 | C29: 0.79236111 | D29: =HOUR(C29) -> 19 | E29: =TEXT(B29,"dddd") -> Thursday | F29: Dine-in | G29: Lamb Kebab | H29: Grills | I29: 2 | J29: 18000 | K29: 36000 | L29: Cash | M29: 0 | O29: Zainab Salim
A30: ORD-00029 | B30: 46058 | C30: 0.80347222 | D30: =HOUR(C30) -> 19 | E30: =TEXT(B30,"dddd") -> Thursday | F30: Delivery | G30: Lamb Kebab | H30: Grills | I30: 1 | J30: 18000 | K30: 15300 | L30: Cash | M30: 0.15 | O30: Zainab Salim
A31: ORD-00030 | B31: 46058 | C31: 0.83333333 | D31: =HOUR(C31) -> 20 | E31: =TEXT(B31,"dddd") -> Thursday | F31: Delivery | G31: Shish Tawook | H31: Grills | I31: 3 | J31: 16000 | K31: 48000 | L31: Card | M31: 0 | O31: Ali Hassan
A32: ORD-00031 | B32: 46058 | C32: 0.88819444 | D32: =HOUR(C32) -> 21 | E32: =TEXT(B32,"dddd") -> Thursday | F32: Dine-in | G32: Chicken Sandwich | H32: Sandwiches | I32: 1 | J32: 6000 | K32: 6000 | L32: Cash | M32: 0 | O32: Omar Jabbar
A33: ORD-00032 | B33: 46058 | C33: 0.89236111 | D33: =HOUR(C33) -> 21 | E33: =TEXT(B33,"dddd") -> Thursday | F33: Dine-in | G33: Shawarma Sandwich | H33: Sandwiches | I33: 1 | J33: 5000 | K33: 5000 | L33: Cash | M33: 0 | O33: Noor Kadhim
A34: ORD-00033 | B34: 46058 | C34: 0.91319444 | D34: =HOUR(C34) -> 21 | E34: =TEXT(B34,"dddd") -> Thursday | F34: Dine-in | G34: Tea | H34: =VLOOKUP(G34,'02_Menu_Lookup'!$A$2:$C$16,2,FALSE) -> Beverages | I34: 2 | J34: 1000 | K34: 2000 | L34: Cash | M34: 0 | O34: Omar Jabbar
A35: ORD-00034 | B35: 46058 | C35: 0.91944444 | D35: =HOUR(C35) -> 22 | E35: =TEXT(B35,"dddd") -> Thursday | F35: Delivery | G35: Lamb Kebab | H35: Grills | I35: 1 | J35: 18000 | K35: 18000 | L35: Cash | M35: 0 | O35: Ali Hassan
A36: ORD-00035 | B36: 46058 | C36: 0.9375 | D36: =HOUR(C36) -> 22 | E36: =TEXT(B36,"dddd") -> Thursday | F36: Dine-in | G36: Soft Drink | H36: Beverages | I36: 1 | J36: 1350 | K36: 1215 | L36: Cash | M36: 0.1 | O36: Omar Jabbar
A37: ORD-00036 | B37: 46058 | C37: 0.94236111 | D37: =HOUR(C37) -> 22 | E37: =TEXT(B37,"dddd") -> Thursday | F37: Dine-in | G37: Baklava | H37: Desserts | I37: 1 | J37: 6000 | K37: 6000 | L37: Cash | M37: 0 | O37: Noor Kadhim
A38: ORD-00037 | B38: 46058 | C38: 0.96805556 | D38: =HOUR(C38) -> 23 | E38: =TEXT(B38,"dddd") -> Thursday | F38: Dine-in | G38: Tea | H38: Beverages | I38: 1 | J38: 1000 | K38: 1000 | L38: Cash | M38: 0 | N38: 5 | O38: Zainab Salim
A39: ORD-00038 | B39: 46059 | C39: 0.47708333 | D39: =HOUR(C39) -> 11 | E39: =TEXT(B39,"dddd") -> Friday | F39: Dine-in | G39: Lamb Kebab | H39: Grills | I39: 1 | J39: 18000 | K39: 18000 | L39: Cash | M39: 0 | O39: Omar Jabbar
A40: ORD-00039 | B40: 46175 | C40: 0.50833333 | D40: =HOUR(C40) -> 12 | E40: =TEXT(B40,"dddd") -> Tuesday | F40: Dine-in | G40: Tea | H40: Beverages | I40: 1 | J40: 1000 | K40: 1000 | L40: Card | M40: 0 | N40: 4 | O40: Noor Kadhim
A41: ORD-00040 | B41: 46059 | C41: 0.59513889 | D41: =HOUR(C41) -> 14 | E41: =TEXT(B41,"dddd") -> Friday | F41: Takeaway | G41: Baklava | H41: Desserts | I41: 1 | J41: 6000 | K41: 6000 | L41: Cash | M41: 0 | N41: 3 | O41: Zainab Salim
A42: ORD-00041 | B42: 46059 | C42: 0.6125 | D42: =HOUR(C42) -> 14 | E42: =TEXT(B42,"dddd") -> Friday | F42: Dine-in | G42: Soft Drink | H42: Beverages | I42: 1 | J42: =K42/I42 -> 1500 | K42: 1500 | L42: Cash | M42: 0 | N42: 5 | O42: Noor Kadhim
A43: ORD-00042 | B43: 46059 | C43: 0.69166667 | D43: =HOUR(C43) -> 16 | E43: =TEXT(B43,"dddd") -> Friday | F43: Delivery | G43: Baklava | H43: Desserts | I43: 1 | J43: 6000 | K43: 6000 | L43: Card | M43: 0 | N43: 4 | O43: Ali Hassan
A44: ORD-00043 | B44: 46059 | C44: 0.80763889 | D44: =HOUR(C44) -> 19 | E44: =TEXT(B44,"dddd") -> Friday | F44: Dine-in | G44: Chicken Sandwich | H44: Sandwiches | I44: 2 | J44: 6000 | K44: 12000 | L44: Cash | M44: 0 | O44: Omar Jabbar
A45: ORD-00044 | B45: 46059 | C45: 0.87222222 | D45: =HOUR(C45) -> 20 | E45: =TEXT(B45,"dddd") -> Friday | F45: Dine-in | G45: Shawarma Sandwich | H45: Sandwiches | I45: 1 | J45: 5000 | K45: 5000 | L45: Card | M45: 0 | O45: Mustafa Karim
A46: ORD-00045 | B46: 46059 | C46: 0.90763889 | D46: =HOUR(C46) -> 21 | E46: =TEXT(B46,"dddd") -> Friday | F46: Dine-in | G46: Shawarma Sandwich | H46: Sandwiches | I46: 2 | J46: 5000 | K46: 8500 | L46: Cash | M46: 0.15 | O46: Ali Hassan
A47: ORD-00046 | B47: 46059 | C47: 0.99513889 | D47: =HOUR(C47) -> 23 | E47: =TEXT(B47,"dddd") -> Friday | F47: Dine-in | G47: Shawarma Sandwich | H47: Sandwiches | I47: 1 | J47: 5000 | K47: 5000 | L47: Card | M47: 0 | N47: 5 | O47: Ali Hassan
A48: ORD-00047 | B48: 46060 | C48: 0.48263889 | D48: =HOUR(C48) -> 11 | E48: =TEXT(B48,"dddd") -> Saturday | F48: Dine-in | G48: Tea | H48: Beverages | I48: 3 | J48: 1000 | K48: 3000 | L48: Card | M48: 0 | N48: 4 | O48: Mustafa Karim
A49: ORD-00048 | B49: 46060 | C49: 0.79791667 | D49: =HOUR(C49) -> 19 | E49: =TEXT(B49,"dddd") -> Saturday | F49: Takeaway | G49: Chicken Sandwich | H49: Sandwiches | I49: 1 | J49: 6000 | K49: 6000 | L49: Cash | M49: 0 | N49: 4 | O49: Zainab Salim
A50: ORD-00049 | B50: 46060 | C50: 0.87777778 | D50: =HOUR(C50) -> 21 | E50: =TEXT(B50,"dddd") -> Saturday | F50: Takeaway | G50: Fresh Lemon Mint | H50: Beverages | I50: 1 | J50: 3000 | K50: 3000 | L50: Cash | M50: 0 | O50: Omar Jabbar
A51: ORD-00050 | B51: 46060 | C51: 0.90347222 | D51: =HOUR(C51) -> 21 | E51: =TEXT(B51,"dddd") -> Saturday | F51: Dine-in | G51: Soft Drink | H51: Beverages | I51: =K51/J51 -> 1 | J51: 1500 | K51: 1500 | L51: Card | M51: 0 | O51: Noor Kadhim
A52: ORD-00051 | B52: 46060 | C52: 0.90486111 | D52: =HOUR(C52) -> 21 | E52: =TEXT(B52,"dddd") -> Saturday | F52: Dine-in | G52: Hummus | H52: Appetizers | I52: 1 | J52: 4000 | K52: =I52*J52 -> 4000 | L52: Cash | M52: 0 | O52: Ali Hassan
A53: ORD-00052 | B53: 46060 | C53: 0.92152778 | D53: =HOUR(C53) -> 22 | E53: =TEXT(B53,"dddd") -> Saturday | F53: Delivery | G53: Chicken Sandwich | H53: Sandwiches | I53: 1 | J53: 6000 | K53: 6000 | L53: Cash | M53: 0 | O53: Noor Kadhim
A54: ORD-00053 | B54: 46060 | C54: 0.94444444 | D54: =HOUR(C54) -> 22 | E54: =TEXT(B54,"dddd") -> Saturday | F54: Delivery | G54: Shawarma Sandwich | H54: Sandwiches | I54: 2 | J54: 5000 | K54: 10000 | L54: Cash | M54: 0 | O54: Mustafa Karim
A55: ORD-00054 | B55: 46061 | C55: 0.80416667 | D55: =HOUR(C55) -> 19 | E55: =TEXT(B55,"dddd") -> Sunday | F55: Dine-in | G55: Hummus | H55: Appetizers | I55: 1 | J55: 4000 | K55: 3600 | L55: Cash | M55: 0.1 | N55: 3 | O55: Zainab Salim
A56: ORD-00055 | B56: 46061 | C56: 0.81736111 | D56: =HOUR(C56) -> 19 | E56: =TEXT(B56,"dddd") -> Sunday | F56: Dine-in | G56: Shish Tawook | H56: Grills | I56: 1 | J56: 16000 | K56: 16000 | L56: Cash | M56: 0 | O56: Omar Jabbar
A57: ORD-00056 | B57: 46061 | C57: 0.84930556 | D57: =HOUR(C57) -> 20 | E57: =TEXT(B57,"dddd") -> Sunday | F57: Dine-in | G57: Fresh Lemon Mint | H57: Beverages | I57: 2 | J57: 3000 | K57: 6000 | L57: Cash | M57: 0 | N57: 4 | O57: Mustafa Karim
A58: ORD-00057 | B58: 46061 | C58: 0.88680556 | D58: =HOUR(C58) -> 21 | E58: =TEXT(B58,"dddd") -> Sunday | F58: Takeaway | G58: Tea | H58: Beverages | I58: 2 | J58: 1000 | K58: 2000 | L58: Cash | M58: 0 | N58: 4 | O58: Omar Jabbar
A59: ORD-00058 | B59: 46061 | C59: 0.90347222 | D59: =HOUR(C59) -> 21 | E59: =TEXT(B59,"dddd") -> Sunday | F59: Dine-in | G59: Falafel Sandwich | H59: Sandwiches | I59: 1 | J59: 3000 | K59: 3000 | L59: Cash | M59: 0 | O59: Ali Hassan
A60: ORD-00059 | B60: 46062 | C60: 0.60347222 | D60: =HOUR(C60) -> 14 | E60: =TEXT(B60,"dddd") -> Monday | F60: Dine-in | G60: Shawarma Sandwich | H60: Sandwiches | I60: 1 | J60: 5000 | K60: 4500 | L60: Cash | M60: 0.1 | O60: Noor Kadhim
A61: ORD-00060 | B61: 46062 | C61: 0.83402778 | D61: =HOUR(C61) -> 20 | E61: =TEXT(B61,"dddd") -> Monday | F61: Dine-in | G61: Fattoush Salad | H61: Appetizers | I61: 3 | J61: 5000 | K61: 15000 | L61: Cash | M61: 0 | N61: 4 | O61: Noor Kadhim
A62: ORD-00061 | B62: 46062 | C62: 0.87916667 | D62: =HOUR(C62) -> 21 | E62: =TEXT(B62,"dddd") -> Monday | F62: Dine-in | G62: Soft Drink | H62: Beverages | I62: 1 | J62: 1500 | K62: 1500 | L62: Cash | M62: 0 | O62: Zainab Salim
A63: ORD-00062 | B63: 46062 | C63: 0.90416667 | D63: =HOUR(C63) -> 21 | E63: =TEXT(B63,"dddd") -> Monday | F63: Delivery | G63: Hummus | H63: Appetizers | I63: 1 | J63: 4000 | K63: 4000 | L63: Cash | M63: 0 | N63: 4 | O63: Omar Jabbar
A64: ORD-00063 | B64: 46062 | C64: 0.92013889 | D64: =HOUR(C64) -> 22 | E64: =TEXT(B64,"dddd") -> Monday | F64: Delivery | G64: Shawarma Sandwich | H64: Sandwiches | I64: 1 | J64: 5000 | K64: 5000 | L64: Cash | M64: 0 | O64: Ali Hassan
A65: ORD-00064 | B65: 46267 | C65: 0.95694444 | D65: =HOUR(C65) -> 22 | E65: =TEXT(B65,"dddd") -> Wednesday | F65: Dine-in | G65: Tea | H65: Beverages | I65: 1 | J65: 1000 | K65: 1000 | L65: Cash | M65: 0 | O65: Mustafa Karim
A66: ORD-00065 | B66: 46063 | C66: 0.77708333 | D66: =HOUR(C66) -> 18 | E66: =TEXT(B66,"dddd") -> Tuesday | F66: Dine-in | G66: Fresh Lemon Mint | H66: Beverages | I66: 1 | J66: 3000 | K66: 3000 | L66: Cash | M66: 0 | O66: Noor Kadhim
A67: ORD-00066 | B67: 46297 | C67: 0.83611111 | D67: =HOUR(C67) -> 20 | E67: =TEXT(B67,"dddd") -> Friday | F67: Dine-in | G67: Soft Drink | H67: Beverages | I67: 1 | J67: 1350 | K67: 1215 | L67: Cash | M67: 0.1 | N67: 4 | O67: Mustafa Karim
A68: ORD-00067 | B68: 46063 | C68: 0.86458333 | D68: =HOUR(C68) -> 20 | E68: =TEXT(B68,"dddd") -> Tuesday | F68: Dine-in | G68: Lamb Kebab | H68: Grills | I68: 1 | J68: 18000 | K68: 18000 | L68: Cash | M68: 0 | N68: 4 | O68: Mustafa Karim
A69: ORD-00068 | B69: 46063 | C69: 0.86875 | D69: =HOUR(C69) -> 20 | E69: =TEXT(B69,"dddd") -> Tuesday | F69: Dine-in | G69: Soft Drink | H69: Beverages | I69: 1 | J69: 1200 | K69: 960 | L69: Cash | M69: 0.2 | O69: Omar Jabbar
A70: ORD-00069 | B70: 46063 | C70: 0.94444444 | D70: =HOUR(C70) -> 22 | E70: =TEXT(B70,"dddd") -> Tuesday | F70: Dine-in | G70: Soft Drink | H70: Beverages | I70: 2 | J70: 1500 | K70: =I70*J70 -> 3000 | L70: Cash | M70: 0 | O70: Noor Kadhim
A71: ORD-00070 | B71: 46063 | C71: 0.94722222 | D71: =HOUR(C71) -> 22 | E71: =TEXT(B71,"dddd") -> Tuesday | F71: Takeaway | G71: Tea | H71: Beverages | I71: 2 | J71: 1000 | K71: 2000 | L71: Card | M71: 0 | O71: Noor Kadhim
A72: ORD-00071 | B72: 46063 | C72: 0.97916667 | D72: =HOUR(C72) -> 23 | E72: =TEXT(B72,"dddd") -> Tuesday | F72: Takeaway | G72: Chicken Tikka | H72: Grills | I72: 2 | J72: =K72/I72 -> 15000 | K72: 30000 | L72: Cash | M72: 0 | N72: 4 | O72: Noor Kadhim
A73: ORD-00072 | B73: 46064 | C73: 0.56736111 | D73: =HOUR(C73) -> 13 | E73: =TEXT(B73,"dddd") -> Wednesday | F73: Dine-in | G73: Hummus | H73: Appetizers | I73: 1 | J73: =K73/I73 -> 4000 | K73: 4000 | L73: Cash | M73: 0 | O73: Ali Hassan
A74: ORD-00073 | B74: 46328 | C74: 0.79583333 | D74: =HOUR(C74) -> 19 | E74: =TEXT(B74,"dddd") -> Monday | F74: Dine-in | G74: Soft Drink | H74: =VLOOKUP(G74,'02_Menu_Lookup'!$A$2:$C$16,2,FALSE) -> Beverages | I74: 1 | J74: 1500 | K74: 1500 | L74: Cash | M74: 0 | N74: 4 | O74: Mustafa Karim
A75: ORD-00074 | B75: 46064 | C75: 0.83402778 | D75: =HOUR(C75) -> 20 | E75: =TEXT(B75,"dddd") -> Wednesday | F75: Dine-in | G75: Lamb Kebab | H75: Grills | I75: 1 | J75: =K75/I75 -> 18000 | K75: 18000 | L75: Cash | M75: 0 | O75: Omar Jabbar
A76: ORD-00075 | B76: 46064 | C76: 0.85347222 | D76: =HOUR(C76) -> 20 | E76: =TEXT(B76,"dddd") -> Wednesday | F76: Dine-in | G76: Chicken Sandwich | H76: Sandwiches | I76: 2 | J76: 6000 | K76: 12000 | L76: Cash | M76: 0 | N76: 4 | O76: Zainab Salim
A77: ORD-00076 | B77: 46064 | C77: 0.87986111 | D77: =HOUR(C77) -> 21 | E77: =TEXT(B77,"dddd") -> Wednesday | F77: Dine-in | G77: Mixed Grill Platter | H77: Grills | I77: 1 | J77: 25000 | K77: 25000 | L77: Card | M77: 0 | O77: Noor Kadhim
A78: ORD-00077 | B78: 46065 | C78: 0.50277778 | D78: =HOUR(C78) -> 12 | E78: =TEXT(B78,"dddd") -> Thursday | F78: Takeaway | G78: Tea | H78: Beverages | I78: 1 | J78: 1000 | K78: 1000 | L78: Cash | M78: 0 | O78: Noor Kadhim
A79: ORD-00078 | B79: 46065 | C79: 0.80763889 | D79: =HOUR(C79) -> 19 | E79: =TEXT(B79,"dddd") -> Thursday | F79: Dine-in | G79: Shish Tawook | H79: Grills | I79: 1 | J79: 16000 | K79: 16000 | L79: Card | M79: 0 | O79: Mustafa Karim
A80: ORD-00079 | B80: 46065 | C80: 0.83333333 | D80: =HOUR(C80) -> 20 | E80: =TEXT(B80,"dddd") -> Thursday | F80: Takeaway | G80: Chicken Sandwich | H80: Sandwiches | I80: 1 | J80: 6000 | K80: 6000 | L80: Cash | M80: 0 | O80: Noor Kadhim
A81: ORD-00080 | B81: 46065 | C81: 0.85486111 | D81: =HOUR(C81) -> 20 | E81: =TEXT(B81,"dddd") -> Thursday | F81: Dine-in | G81: Mixed Grill Platter | H81: Grills | I81: 1 | J81: 25000 | K81: 22500 | L81: Cash | M81: 0.1 | N81: 4 | O81: Zainab Salim
A82: ORD-00081 | B82: 46065 | C82: 0.85763889 | D82: =HOUR(C82) -> 20 | E82: =TEXT(B82,"dddd") -> Thursday | F82: Dine-in | G82: Falafel Sandwich | H82: Sandwiches | I82: 1 | J82: 3000 | K82: 3000 | L82: Cash | M82: 0 | N82: 4 | O82: Ali Hassan
A83: ORD-00082 | B83: 46065 | C83: 0.88611111 | D83: =HOUR(C83) -> 21 | E83: =TEXT(B83,"dddd") -> Thursday | F83: Takeaway | G83: Shawarma Sandwich | H83: Sandwiches | I83: 1 | J83: 5000 | K83: 5000 | L83: Cash | M83: 0 | O83: Ali Hassan
A84: ORD-00083 | B84: 46065 | C84: 0.91111111 | D84: =HOUR(C84) -> 21 | E84: =TEXT(B84,"dddd") -> Thursday | F84: Dine-in | G84: Falafel Sandwich | H84: Sandwiches | I84: 1 | J84: 3000 | K84: 3000 | L84: Cash | M84: 0 | N84: 3 | O84: Ali Hassan
A85: ORD-00084 | B85: 46065 | C85: 0.96319444 | D85: =HOUR(C85) -> 23 | E85: =TEXT(B85,"dddd") -> Thursday | F85: Dine-in | G85: Shish Tawook | H85: Grills | I85: 3 | J85: 16000 | K85: 43200 | L85: Cash | M85: 0.1 | O85: Omar Jabbar
A86: ORD-00085 | B86: 46065 | C86: 0.97708333 | D86: =HOUR(C86) -> 23 | E86: =TEXT(B86,"dddd") -> Thursday | F86: Dine-in | G86: Shawarma Sandwich | H86: Sandwiches | I86: 2 | J86: 5000 | K86: 10000 | L86: Card | M86: 0 | O86: Noor Kadhim
A87: ORD-00086 | B87: 46065 | C87: 0.98819444 | D87: =HOUR(C87) -> 23 | E87: =TEXT(B87,"dddd") -> Thursday | F87: Dine-in | G87: Lamb Kebab | H87: Grills | I87: 3 | J87: 18000 | K87: 54000 | L87: Cash | M87: 0 | O87: Noor Kadhim
A88: ORD-00087 | B88: 46065 | C88: 0.99305556 | D88: =HOUR(C88) -> 23 | E88: =TEXT(B88,"dddd") -> Thursday | F88: Dine-in | G88: Fresh Lemon Mint | H88: Beverages | I88: 1 | J88: 3000 | K88: 3000 | L88: Cash | M88: 0 | N88: 4 | O88: Mustafa Karim
A89: ORD-00088 | B89: 46066 | C89: 0.57986111 | D89: =HOUR(C89) -> 13 | E89: =TEXT(B89,"dddd") -> Friday | F89: Takeaway | G89: Mixed Grill Platter | H89: Grills | I89: 1 | J89: 25000 | K89: 25000 | L89: Cash | M89: 0 | O89: Mustafa Karim
A90: ORD-00089 | B90: 46066 | C90: 0.6125 | D90: =HOUR(C90) -> 14 | E90: =TEXT(B90,"dddd") -> Friday | F90: Dine-in | G90: Baklava | H90: =VLOOKUP(G90,'02_Menu_Lookup'!$A$2:$C$16,2,FALSE) -> Desserts | I90: 1 | J90: 6000 | K90: 6000 | L90: Cash | M90: 0 | O90: Noor Kadhim
A91: ORD-00090 | B91: 46066 | C91: 0.74236111 | D91: =HOUR(C91) -> 17 | E91: =TEXT(B91,"dddd") -> Friday | F91: Dine-in | G91: Mixed Grill Platter | H91: Grills | I91: 1 | J91: 25000 | K91: 20000 | L91: Cash | M91: 0.2 | O91: Omar Jabbar
A92: ORD-00091 | B92: 46066 | C92: 0.75347222 | D92: =HOUR(C92) -> 18 | E92: =TEXT(B92,"dddd") -> Friday | F92: Dine-in | G92: Fresh Lemon Mint | H92: Beverages | I92: 1 | J92: 3000 | K92: 3000 | L92: Cash | M92: 0 | O92: Omar Jabbar
A93: ORD-00092 | B93: 46066 | C93: 0.76458333 | D93: =HOUR(C93) -> 18 | E93: =TEXT(B93,"dddd") -> Friday | F93: Dine-in | G93: Falafel Sandwich | H93: Sandwiches | I93: 2 | J93: 3000 | K93: 6000 | L93: Cash | M93: 0 | O93: Mustafa Karim
A94: ORD-00093 | B94: 46066 | C94: 0.80069444 | D94: =HOUR(C94) -> 19 | E94: =TEXT(B94,"dddd") -> Friday | F94: Dine-in | G94: Tea | H94: Beverages | I94: 2 | J94: 1000 | K94: 2000 | L94: Cash | M94: 0 | O94: Noor Kadhim
A95: ORD-00094 | B95: 46066 | C95: 0.84027778 | D95: =HOUR(C95) -> 20 | E95: =TEXT(B95,"dddd") -> Friday | F95: Dine-in | G95: Baklava | H95: Desserts | I95: 1 | J95: 6000 | K95: 6000 | L95: Cash | M95: 0 | N95: 4 | O95: Omar Jabbar
A96: ORD-00095 | B96: 46066 | C96: 0.84305556 | D96: =HOUR(C96) -> 20 | E96: =TEXT(B96,"dddd") -> Friday | F96: Dine-in | G96: Falafel Sandwich | H96: Sandwiches | I96: 1 | J96: 3000 | K96: 3000 | L96: Card | M96: 0 | O96: Ali Hassan
A97: ORD-00096 | B97: 46066 | C97: 0.85347222 | D97: =HOUR(C97) -> 20 | E97: =TEXT(B97,"dddd") -> Friday | F97: Dine-in | G97: Falafel Sandwich | H97: Sandwiches | I97: 1 | J97: 3000 | K97: 3000 | L97: Cash | M97: 0 | O97: Ali Hassan
A98: ORD-00097 | B98: 46066 | C98: 0.86458333 | D98: =HOUR(C98) -> 20 | E98: =TEXT(B98,"dddd") -> Friday | F98: Dine-in | G98: Falafel Sandwich | H98: Sandwiches | I98: 1 | J98: 3000 | K98: 3000 | L98: Cash | M98: 0 | O98: Noor Kadhim
A99: ORD-00098 | B99: 46066 | C99: 0.87916667 | D99: =HOUR(C99) -> 21 | E99: =TEXT(B99,"dddd") -> Friday | F99: Delivery | G99: Lamb Kebab | H99: Grills | I99: 1 | J99: 18000 | K99: 18000 | L99: Cash | M99: 0 | N99: 4 | O99: Noor Kadhim
A100: ORD-00099 | B100: 46066 | C100: 0.87986111 | D100: =HOUR(C100) -> 21 | E100: =TEXT(B100,"dddd") -> Friday | F100: Dine-in | G100: Chicken Sandwich | H100: Sandwiches | I100: 2 | J100: 6000 | K100: 12000 | L100: Cash | M100: 0 | O100: Mustafa Karim
...

Sheet 02_Menu_Lookup
A1: item_name | B1: category | C1: unit_price
A2: Mixed Grill Platter | B2: Grills | C2: 25000
A3: Lamb Kebab | B3: Grills | C3: 18000
A4: Shish Tawook | B4: Grills | C4: 16000
A5: Chicken Tikka | B5: Grills | C5: 15000
A6: Chicken Sandwich | B6: Sandwiches | C6: 6000
A7: Shawarma Sandwich | B7: Sandwiches | C7: 5000
A8: Falafel Sandwich | B8: Sandwiches | C8: 3000
A9: Fattoush Salad | B9: Appetizers | C9: 5000
A10: Mutabbal | B10: Appetizers | C10: 4500
A11: Hummus | B11: Appetizers | C11: 4000
A12: Kunafa | B12: Desserts | C12: 7000
... A16: Tea | B16: Beverages | C16: 1000

Sheet 03-ِAnalysis
A1: order_date | B1: (ALL)
A2: Monthly Revenue by Channel | G2: Peak Hours Matrix by Day of Week
B3: ز | G3: .2 | H3: . | Q3: Sales Breakdown by Category
B4: Delivery | C4: Dine-in | D4: Takeaway | E4: Grand Total | G4: Hour | H4: Sunday | I4: Monday | J4: Tuesday | K4: Wednesday | L4: Thursday | M4: Friday | N4: Saturday | O4: Grand Total | Q4: category | R4: SUM o total_price
B5: 4162330 | C5: 6971020 | D5: 2849025 | E5: 13982375 | G5: 11 | H5: 3 | I5: 3 | J5: 1 | K5: 3 | L5: 1 | M5: 3 | N5: 2 | O5: 16 | Q5: Appetizers | R5: 0.0689021
G6: 12 | H6: 4 | I6: 4 | J6: 5 | K6: 9 | L6: 15 | M6: 11 | N6: 11 | O6: 59 | Q6: Beverages | R6: 0.054502186
G7: 13 | H7: 5 | I7: 12 | J7: 13 | K7: 18 | L7: 15 | M7: 17 | N7: 17 | O7: 97 | Q7: Desserts | R7: 0.057357924
G8: 14 | H8: 10 | I8: 7 | J8: 7 | K8: 11 | L8: 16 | M8: 23 | N8: 19 | O8: 93 | Q8: Grills | R8: 0.64173004
G9: 15 | H9: 4 | I9: 6 | J9: 7 | K9: 6 | L9: 11 | M9: 14 | N9: 5 | O9: 53 | Q9: Sandwiches | R9: 0.17750776
G10: 16 | H10: 3 | I10: 3 | J10: 3 | K10: 6 | L10: 3 | M10: 8 | N10: 8 | O10: 34 | Q10: Grand Total | R10: 1
G11: 17 | H11: 6 | I11: 4 | J11: 4 | K11: 6 | L11: 9 | M11: 7 | N11: 5 | O11: 41
G12: 18 | H12: 7 | I12: 5 | J12: 8 | K12: 8 | L12: 15 | M12: 15 | N12: 9 | O12: 67
G13: 19 | H13: 17 | I13: 22 | J13: 18 | K13: 20 | L13: 25 | M13: 42 | N13: 35 | O13: 179
G14: 20 | H14: 29 | I14: 35 | J14: 28 | K14: 37 | L14: 30 | M14: 54 | N14: 54 | O14: 267
G15: 21 | H15: 23 | I15: 31 | J15: 19 | K15: 37 | L15: 44 | M15: 64 | N15: 48 | O15: 266
G16: 22 | H16: 24 | I16: 24 | J16: 22 | K16: 20 | L16: 33 | M16: 38 | N16: 36 | O16: 197
G17: 23 | H17: 10 | I17: 5 | J17: 6 | K17: 14 | L17: 24 | M17: 10 | N17: 12 | O17: 81
G18: Grand Total | H18: 145 | I18: 161 | J18: 141 | K18: 195 | L18: 241 | M18: 306 | N18: 261 | O18: 1450
A22: Average Customer Rating per Item | D22: Total Orders by Hour of Day | G22: Monthly Revenue Share by Payment Method | L22: Top 10 Best Selling Items
A23: item_name | B23: AVERAGE rating | D23: hour | E23: COUNTA of order_id | G23: . | H23: .
A24: Baklava | B24: 3.8 | D24: 11 | E24: 16 | G24: order_date - Month | H24: Cash | I24: Card | J24: Grand Total | L24: item_name | M24: SUM of quantity | N24: SUM of total_price
A25: Chicken Sandwich | B25: 4.04 | D25: 12 | E25: 59 | G25: Jan | H25: 0.0014303722 | I25: 0.00035759304 | J25: 0.0017879652 | L25: Baklava | M25: 45 | N25: 263700
A26: Chicken Tikka | B26: 4.0571429 | D26: 13 | E26: 97 | G26: Feb | H26: 0.12328199 | I26: 0.038437676 | J26: 0.16171966 | L26: Chicken Sandwich | M26: 164 | N26: 968100
A27: Falafel Sandwich | B27: 3.75 | D27: 14 | E27: 93 | G27: Mar | H27: 0.12233794 | I27: 0.034935052 | J27: 0.157273 | L27: Chicken Tikka | M27: 122 | N27: 1807650
A28: Fattoush Salad | B28: 3.8947368 | D28: 15 | E28: 53 | G28: Apr | H28: 0.11943643 | I28: 0.036726593 | J28: 0.15616303 | L28: Falafel Sandwich | M28: 147 | N28: 426780
A29: Fresh Lemon Mint | B29: 4.5833333 | D29: 16 | E29: 34 | G29: May | H29: 0.12065904 | I29: 0.056225069 | J29: 0.17688411 | L29: Fattoush Salad | M29: 75 | N29: 369500
A30: Hummus | B30: 4.1219512 | D30: 17 | E30: 41 | G30: Jun | H30: 0.086085161 | I30: 0.071643766 | J30: 0.15772893 | L30: Fresh Lemon Mint | M30: 43 | N30: 128400
A31: Kunafa | B31: 4.2173913 | D31: 18 | E31: 67 | G31: Jul | H31: 0.092437801 | I31: 0.087445445 | J31: 0.17988325 | L31: Hummus | M31: 116 | N31: 456890
A32: Lamb Kebab | B32: 4.15625 | D32: 19 | E32: 179 | G32: Aug | H32: 0.0010012605 | I32: 0.00040765607 | J32: 0.0014089166 | L32: Kunafa | M32: 78 | N32: 538300
A33: Mixed Grill Platter | B33: 4.3428571 | D33: 20 | E33: 267 | G33: Sep | H33: 0.0018594838 | J33: 0.0018594838 | L33: Lamb Kebab | M33: 108 | N33: 1908900
A34: Mutabbal | B34: 2.5 | D34: 21 | E34: 266 | G34: Oct | H34: 0.00040872885 | I34: 0.0015018908 | J34: 0.0019106196 | L34: Mixed Grill Platter | M34: 134 | N34: 3260000
A35: Shawarma Sandwich | B35: 4.2131148 | D35: 22 | E35: 197 | G35: Nov | H35: 0.0022009852 | I35: 0.00071518608 | J35: 0.0029161713 | L35: Mutabbal | M35: 31 | N35: 137025
A36: Shish Tawook | B36: 4.2647059 | D36: 23 | E36: 81 | G36: Dec | H36: 0.00010727791 | I36: 0.00035759304 | J36: 0.00046487095 | L36: Shawarma Sandwich | M36: 222 | N36: 1087100
A37: Soft Drink | B37: 3.7972973 | D37: Grand Total | E37: 1450 | G37: Grand Total | H37: 0.67124648 | I37: 0.32875352 | J37: 1 | L37: Shish Tawook | M37: 128 | N37: 1996360
A38: Tea | B38: 3.9538462 | L38: Soft Drink | M38: 271 | N38: 397920
A39: Grand Total | B39: 4.0128205 | L39: Tea | M39: 239 | N39: 235750
L40: Grand Total | M40: 1923 | N40: 13982375

Sheet 04_Charts

Sheet 05_Cleaning_Log
A1: Log ID | B1: Issue Identified_Column(s) | C1: Original Problem Description | D1: Action Taken_Formula | E1: Tool Used_Row Count | F1: Impact
A2: Duplicate Records | B2: All Columns (A:Z) | C2: 50 identical duplicate order rows causing inflated sales metrics and distorted counts. | D2: Highlighted duplicate primary keys using Conditional Formatting, reviewed for exact matches, and removed all 50 duplicate records to streamline the dataset to 1,450 unique orders.. | E2: Tool Used: =COUNTIF(A:A, A1) > 1 + Data Cleanup tool / Remove Duplicates | F2: 50 rows removed (Reduced 1,500 to 1,450)
A3: Text Standardisation & Typo Correction | B3: item_name, category, payment_method, server_name | C3: Inconsistent text casing (e.g., lowercase entries), inconsistent payment method tags (e.g., CASH vs cash), typos in server names, and trailing whitespace across product and transaction details. | D3: Extracted unique string lists to locate all variant spellings and casing errors, trimmed hidden spaces, standardized text to Proper Case, and replaced incorrect entries with unified standard terms. | E3: =TRIM(), =PROPER(), =UNIQUE(), and Find & Replace | F3: 100+ rows cleaned and standardized across text columns
A4: Data Type & Formatting Corrections | B4: order_date, unit_price, total_price | C4: Dates were formatted as raw numbers/general text, and monetary values lacked standard currency formatting and thousand separators. | D4: Converted text numbers in the date column to proper Date data types (YYYY-MM-DD) and applied financial number formatting (comma separators) to price columns for clean visual presentation and accurate mathematical operations. | E4: Format $\rightarrow$ Number $\rightarrow$ Date and Format $\rightarrow$ Number $\rightarrow$ Financial / Custom Currency | F4: 1,450 clean rows
A5: Discount Logic & Price Reconciliation | B5: discount_pct, total_price, unit_price | C5: Discrepancies where discounts were flagged but not applied to totals. Additionally, text currency symbols (IQD) inside cells blocked direct mathematical formula evaluation. | D5: Temporarily removed the text currency symbol IQD from price cells to enable numeric math operations. Used a temporary helper column with a filter to recalculate true net totals for the 204 discounted orders, pasted the calculated values into total_price, and finally reapplied IQD standard currency formatting across the column. | E5: unit_price * quantity * (1 - (discount_pct / 100))via Helper Column + Filter + Paste Values + Custom Currency Formatting | F5: 204 discounted orders reconciled
A6: Missing Values & Data Imputation | B6: category, unit_price, total_price, quantity | C6: Missing values across key transactional fields (category: 87, unit_price: 68, total_price: 65, quantity: 25) following duplicate removal. Transformation / Action Taken: Imputed missing values to preserve record integrity. Cross-referenced item names against the master lookup tab (02_Menu_Lookup) to restore categories and base unit prices, while mathematically calculating missing total prices and quantities using dependent arithmetic formulas. | D6: Imputed missing values to preserve record integrity. Cross-referenced item names against the master lookup tab (02_Menu_Lookup) to restore categories and base unit prices, while mathematically calculating missing total prices and quantities using arithmetic formulas. | E6: IFERROR(VLOOKUP(A2, '02_Menu_Lookup'!A:C, 2, FALSE), unit_price * quantity) | F6: 245 missing data points imputed across 1,450 records
